ovos_solver_dialogpt/__init__.py
ovos_solver_dialogpt/version.py
ovos_solver_dialogpt_plugin-0.0.0a2.dist-info/LICENSE
ovos_solver_dialogpt_plugin-0.0.0a2.dist-info/METADATA
ovos_solver_dialogpt_plugin-0.0.0a2.dist-info/WHEEL
ovos_solver_dialogpt_plugin-0.0.0a2.dist-info/entry_points.txt
ovos_solver_dialogpt_plugin-0.0.0a2.dist-info/top_level.txt
ovos_solver_dialogpt_plugin-0.0.0a2.dist-info/zip-safe
ovos_solver_dialogpt_plugin-0.0.0a2.dist-info/RECORD
