Metadata-Version: 2.1
Name: ovos-solver-dialogpt-plugin
Version: 0.0.0a2
Summary: A question solver plugin for ovos
Home-page: https://github.com/OpenVoiceOS/ovos-solver-plugin-dialogpt
Author: jarbasai
Author-email: jarbasai@mailfence.com
License: MIT
Keywords: ovos plugin utterance fallback query
Platform: UNKNOWN
Requires-Dist: transformers
Requires-Dist: ovos-plugin-manager
